transdata/__init__.py
transdata/exportdata.py
transdata/importdata.py
transdata/transdata.py
transdata-1.1.3.dist-info/METADATA
transdata-1.1.3.dist-info/WHEEL
transdata-1.1.3.dist-info/top_level.txt
transdata-1.1.3.dist-info/RECORD
